sequestrum/__init__.py
sequestrum/arguments.py
sequestrum/argumentsModule.py
sequestrum/commands.py
sequestrum/commandsModule.py
sequestrum/directories.py
sequestrum/directoryModule.py
sequestrum/errors.py
sequestrum/errorsModule.py
sequestrum/logging.py
sequestrum/loggingModule.py
sequestrum/options.py
sequestrum/packageModule.py
sequestrum/sequestrum.py
sequestrum/symlink.py
sequestrum/symlinkModule.py
sequestrum-1.6.4.dist-info/METADATA
sequestrum-1.6.4.dist-info/RECORD
sequestrum-1.6.4.dist-info/WHEEL
sequestrum-1.6.4.dist-info/entry_points.txt
sequestrum-1.6.4.dist-info/top_level.txt
