Metadata-Version: 2.1
Name: sequestrum
Version: 1.6.4
Summary: Modern Dotfile Manager
Home-page: http://github.com/iiPlasma/sequestrum
Author: Ivy Zhang
Author-email: ZIvy042003@gmail.com
License: MIT
Platform: UNKNOWN
Requires-Dist: pyyaml (==3.13)
